[
    { "id": 26, "nome": "Introdução à Programação", "periodoIdeal": 1, "preRequisitos": [], "cargaHoraria": 128, "creditos": 8, "tipo": "obrigatoria" },
    { "id": 21, "nome": "Fundamentos de Matemática para Computação", "periodoIdeal": 1, "preRequisitos": [], "cargaHoraria": 64, "creditos": 4, "tipo": "obrigatoria" },
    { "id": 7, "nome": "Cálculo 1A", "periodoIdeal": 1, "preRequisitos": [], "cargaHoraria": 96, "creditos": 6, "tipo": "obrigatoria" },
    { "id": 12, "nome": "Computação e Sociedade", "periodoIdeal": 1, "preRequisitos": [], "cargaHoraria": 32, "creditos": 2, "tipo": "obrigatoria" },
    { "id": 2, "nome": "Algoritmos e Estruturas de Dados 1", "periodoIdeal": 2, "preRequisitos": [26], "cargaHoraria": 64, "creditos": 4, "tipo": "obrigatoria" },
    { "id": 29, "nome": "Lógica Matemática", "periodoIdeal": 2, "preRequisitos": [21], "cargaHoraria": 64, "creditos": 4, "tipo": "obrigatoria" },
    { "id": 8, "nome": "Cálculo 2A", "periodoIdeal": 2, "preRequisitos": [7], "cargaHoraria": 96, "creditos": 6, "tipo": "obrigatoria" },
    { "id": 19, "nome": "Física I", "periodoIdeal": 2, "preRequisitos": [7], "cargaHoraria": 64, "creditos": 4, "tipo": "obrigatoria" },
    { "id": 22, "nome": "Geometria Analítica", "periodoIdeal": 2, "preRequisitos": [], "cargaHoraria": 64, "creditos": 4, "tipo": "obrigatoria" },
    { "id": 3, "nome": "Algoritmos e Estruturas de Dados 2", "periodoIdeal": 3, "preRequisitos": [2], "cargaHoraria": 64, "creditos": 4, "tipo": "obrigatoria" },
    { "id": 30, "nome": "Matemática Discreta", "periodoIdeal": 3, "preRequisitos": [21], "cargaHoraria": 64, "creditos": 4, "tipo": "obrigatoria" },
    { "id": 33, "nome": "Probabilidade e Estatística A", "periodoIdeal": 3, "preRequisitos": [7], "cargaHoraria": 64, "creditos": 4, "tipo": "obrigatoria" },
    { "id": 1, "nome": "Álgebra Linear", "periodoIdeal": 3, "preRequisitos": [], "cargaHoraria": 64, "creditos": 4, "tipo": "obrigatoria" },
    { "id": 20, "nome": "Física III", "periodoIdeal": 3, "preRequisitos": [19], "cargaHoraria": 64, "creditos": 4, "tipo": "obrigatoria" },
    { "id": 31, "nome": "Metodologia de Pesquisa em Computação", "periodoIdeal": 3, "preRequisitos": [], "cargaHoraria": 32, "creditos": 2, "tipo": "obrigatoria" },
    { "id": 10, "nome": "Circuitos Digitais", "periodoIdeal": 4, "preRequisitos": [21], "cargaHoraria": 64, "creditos": 4, "tipo": "obrigatoria" },
    { "id": 18, "nome": "Equações Diferenciais", "periodoIdeal": 4, "preRequisitos": [1,8], "cargaHoraria": 64, "creditos": 4, "tipo": "obrigatoria" },
    { "id": 34, "nome": "Programação Orientada a Objetos", "periodoIdeal": 4, "preRequisitos": [26], "cargaHoraria": 64, "creditos": 4, "tipo": "obrigatoria" },
    { "id": 32, "nome": "Pesquisa Operacional", "periodoIdeal": 4, "preRequisitos": [], "cargaHoraria": 64, "creditos": 4, "tipo": "obrigatoria" },
    { "id": 43, "nome": "Teoria dos Grafos", "periodoIdeal": 4, "preRequisitos": [30], "cargaHoraria": 64, "creditos": 4, "tipo": "obrigatoria" },
    { "id": 15, "nome": "Eletrônica para Computação", "periodoIdeal": 5, "preRequisitos": [20], "cargaHoraria": 96, "creditos": 6, "tipo": "obrigatoria" },
    { "id": 9, "nome": "Cálculo Numérico", "periodoIdeal": 5, "preRequisitos": [18], "cargaHoraria": 64, "creditos": 4, "tipo": "obrigatoria" },
    { "id": 4, "nome": "Análise e Projeto de Algoritmos", "periodoIdeal": 5, "preRequisitos": [3], "cargaHoraria": 64, "creditos": 4, "tipo": "obrigatoria" },
    { "id": 5, "nome": "Arquitetura de Computadores", "periodoIdeal": 5, "preRequisitos": [21], "cargaHoraria": 64, "creditos": 4, "tipo": "obrigatoria" },
    { "id": 42, "nome": "Software Básico", "periodoIdeal": 5, "preRequisitos": [2], "cargaHoraria": 64, "creditos": 4, "tipo": "obrigatoria" },
    { "id": 6, "nome": "Banco de Dados", "periodoIdeal": 6, "preRequisitos": [29], "cargaHoraria": 64, "creditos": 4, "tipo": "obrigatoria" },
    { "id": 17, "nome": "Engenharia de Software", "periodoIdeal": 6, "preRequisitos": [], "cargaHoraria": 64, "creditos": 4, "tipo": "obrigatoria" },
    { "id": 27, "nome": "Linguagens e Paradigmas de Programação", "periodoIdeal": 6, "preRequisitos": [26], "cargaHoraria": 64, "creditos": 4, "tipo": "obrigatoria" },
    { "id": 28, "nome": "Linguagens Formais e Autômatos", "periodoIdeal": 6, "preRequisitos": [21], "cargaHoraria": 64, "creditos": 4, "tipo": "obrigatoria" },
    { "id": 41, "nome": "Sistemas Operacionais", "periodoIdeal": 6, "preRequisitos": [5,2], "cargaHoraria": 64, "creditos": 4, "tipo": "obrigatoria" },
    { "id": 25, "nome": "Introdução à Computabilidade e à Complexidade", "periodoIdeal": 7, "preRequisitos": [4,28], "cargaHoraria": 64, "creditos": 4, "tipo": "obrigatoria" },
    { "id": 16, "nome": "Engenharia de Requisitos", "periodoIdeal": 7, "preRequisitos": [], "cargaHoraria": 64, "creditos": 4, "tipo": "obrigatoria" },
    { "id": 40, "nome": "Sistemas Gerenciadores de Banco de Dados", "periodoIdeal": 7, "preRequisitos": [6], "cargaHoraria": 64, "creditos": 4, "tipo": "obrigatoria" },
    { "id": 38, "nome": "Redes de Computadores 1", "periodoIdeal": 7, "preRequisitos": [], "cargaHoraria": 64, "creditos": 4, "tipo": "obrigatoria" },
    { "id": 36, "nome": "Projeto Final de Curso 1", "periodoIdeal": 8, "preRequisitos": [], "cargaHoraria": 64, "creditos": 4, "tipo": "obrigatoria" },
    { "id": 35, "nome": "Projeto de Software", "periodoIdeal": 8, "preRequisitos": [17,34], "cargaHoraria": 64, "creditos": 4, "tipo": "obrigatoria" },
    { "id": 13, "nome": "Computação Gráfica", "periodoIdeal": 8, "preRequisitos": [22], "cargaHoraria": 64, "creditos": 4, "tipo": "obrigatoria" },
    { "id": 23, "nome": "Inteligência Artificial", "periodoIdeal": 8, "preRequisitos": [2,29,33], "cargaHoraria": 64, "creditos": 4, "tipo": "obrigatoria" },
    { "id": 39, "nome": "Sistemas Distribuídos", "periodoIdeal": 8, "preRequisitos": [38], "cargaHoraria": 64, "creditos": 4, "tipo": "obrigatoria" },
    { "id": 37, "nome": "Projeto Final de Curso 2", "periodoIdeal": 9, "preRequisitos": [36], "cargaHoraria": 64, "creditos": 4, "tipo": "obrigatoria" },
    { "id": 24, "nome": "Interação Humano Computador", "periodoIdeal": 9, "preRequisitos": [2], "cargaHoraria": 64, "creditos": 4, "tipo": "obrigatoria" },
    { "id": 11, "nome": "Compiladores", "periodoIdeal": 9, "preRequisitos": [28,3], "cargaHoraria": 64, "creditos": 4, "tipo": "obrigatoria" },
    { "id": 14, "nome": "Computação Paralela", "periodoIdeal": 9, "preRequisitos": [39], "cargaHoraria": 64, "creditos": 4, "tipo": "obrigatoria" }
]
